[
  {
    "Prefab": "Pillar.json",
    "Position": [ 29, 4, 50],
	"Rotate": [0.0, 90.0, 0.0],
	"Scale": [2, 10, 40]
  },
  {
    "Prefab": "Pillar.json",
    "Position": [ 50, 4, 31],
	"Scale": [2, 10, 40]
  },
  {
    "Prefab": "Pillar.json",
    "Position": [ 50, 4, -31],
	"Scale": [2, 10, 40]
  },
  {
    "Prefab": "Pillar.json",
    "Position": [ 29, 4, -50],
	"Rotate": [0.0, 90.0, 0.0],
	"Scale": [2, 10, 40]
  },
  {
    "Prefab": "Pillar.json",
    "Position": [ -29, 4, -50],
	"Rotate": [0.0, 90.0, 0.0],
	"Scale": [2, 10, 40]
  },
  {
    "Prefab": "Pillar.json",
    "Position": [ -50, 4, -31],
	"Scale": [2, 10, 40]
  },
  {
    "Prefab": "Pillar.json",
    "Position": [ -50, 4, 31],
	"Scale": [2, 10, 40]
  },
  {
    "Prefab": "Pillar.json",
    "Position": [ -29, 4, 50],
	"Rotate": [0.0, 90.0, 0.0],
	"Scale": [2, 10, 40]
  },


  {
    "Prefab": "Pillar.json",
    "Position": [ -10, 4, 61],
	"Scale": [2, 10, 20]
  },
  {
    "Prefab": "Pillar.json",
    "Position": [ 10, 4, 61],
	"Scale": [2, 10, 20]
  },
  {
    "Prefab": "Pillar.json",
    "Position": [ 61, 4, 12],
	"Rotate": [0.0, 90.0, 0.0],
	"Scale": [2, 10, 20]
  },
  {
    "Prefab": "Pillar.json",
    "Position": [ 61, 4, -12],
	"Rotate": [0.0, 90.0, 0.0],
	"Scale": [2, 10, 20]
  },
  {
    "Prefab": "Pillar.json",
    "Position": [ -10, 4, -61],
	"Scale": [2, 10, 20]
  },
  {
    "Prefab": "Pillar.json",
    "Position": [ 10, 4, -61],
	"Scale": [2, 10, 20]
  },
  {
    "Prefab": "Pillar.json",
    "Position": [ -61, 4, -12],
	"Rotate": [0.0, 90.0, 0.0],
	"Scale": [2, 10, 20]
  },
  {
    "Prefab": "Pillar.json",
    "Position": [ -61, 4, 12],
	"Rotate": [0.0, 90.0, 0.0],
	"Scale": [2, 10, 20]
  },

  {
    "Prefab": "Pillar.json",
    "Position": [ 0, 14, 127.5],
	"Rotate": [0.0, 90.0, 0.0],
	"Scale": [2, 30, 257]
  },
  {
    "Prefab": "Pillar.json",
    "Position": [ 127.5, 14, 0],
	"Scale": [2, 30, 257]
  },
  {
    "Prefab": "Pillar.json",
    "Position": [0, 14, -128.5],
	"Rotate": [0.0, 90.0, 0.0],
	"Scale": [2, 30, 257]
  },
  {
    "Prefab": "Pillar.json",
    "Position": [ -128.5, 14, 0],
	"Scale": [2, 30, 257]
  },

  "Sun.json"
]